claude_cad/__init__.py
claude_cad/mock_server.py
claude_cad/model_generator.py
claude_cad/server.py
claude_cad/utils.py
claude_cad-0.1.7.dist-info/licenses/LICENSE
claude_cad-0.1.7.dist-info/METADATA
claude_cad-0.1.7.dist-info/WHEEL
claude_cad-0.1.7.dist-info/entry_points.txt
claude_cad-0.1.7.dist-info/top_level.txt
claude_cad-0.1.7.dist-info/RECORD
