Metadata-Version: 2.4
Name: claude_cad
Version: 0.1.7
Summary: An MCP plugin for creating 3D models with Claude AI using CadQuery
Home-page: https://github.com/bronson/claude_cad
Author: Bronson Dunbar
Author-email: bronson@example.com
Project-URL: Bug Tracker, https://github.com/bronson/claude_cad/issues
Project-URL: Documentation, https://github.com/bronson/claude_cad#readme
Project-URL: Source Code, https://github.com/bronson/claude_cad
Classifier: Development Status :: 3 - Alpha
Classifier: Intended Audience :: Developers
Classifier: License :: OSI Approved :: Apache Software License
Classifier: Programming Language :: Python :: 3
Classifier: Programming Language :: Python :: 3.9
Classifier: Programming Language :: Python :: 3.10
Classifier: Programming Language :: Python :: 3.11
Requires-Python: >=3.9
License-File: LICENSE
Requires-Dist: cadquery>=2.0.0
Requires-Dist: mcp>=1.6.0
Dynamic: author
Dynamic: author-email
Dynamic: classifier
Dynamic: description
Dynamic: description-content-type
Dynamic: home-page
Dynamic: license-file
Dynamic: project-url
Dynamic: requires-dist
Dynamic: requires-python
Dynamic: summary
